toarray/__init__.py
toarray/iterable_to_array.py
toarray-0.2.1.dist-info/LICENSE.md
toarray-0.2.1.dist-info/METADATA
toarray-0.2.1.dist-info/WHEEL
toarray-0.2.1.dist-info/top_level.txt
toarray-0.2.1.dist-info/RECORD
