Metadata-Version: 2.1
Name: toarray
Version: 0.2.1
Summary: Small Python package for converting iterables to arrays.
Home-page: https://github.com/eddiethedean/toarray
Author: Odos Matthews
Author-email: odosmatthews@gmail.com
License: MIT
Classifier: License :: OSI Approved :: MIT License
Classifier: Programming Language :: Python :: 3
Classifier: Programming Language :: Python :: 3.6
Requires-Python: >=3.6
License-File: LICENSE.md
Requires-Dist: more-itertools
